gym_connect/__init__.py
gym_connect/envs/__init__.py
gym_connect/envs/connect_env.py
gym_connect-0.0.4.4.dist-info/LICENSE
gym_connect-0.0.4.4.dist-info/METADATA
gym_connect-0.0.4.4.dist-info/WHEEL
gym_connect-0.0.4.4.dist-info/top_level.txt
gym_connect-0.0.4.4.dist-info/RECORD
